{
    "className": "org.joget.apps.form.model.Form",
    "properties": {
        "id": "md16livestockType",
        "name": "MD.16 - Livestock Type",
        "tableName": "md16livestockType",
        "loadBinder": {
            "className": "org.joget.apps.form.lib.WorkflowFormBinder",
            "properties": {}
        },
        "storeBinder": {
            "className": "org.joget.apps.form.lib.WorkflowFormBinder",
            "properties": {}
        },
        "description": "Master data for livestock types with category reference for cascading dropdowns",
        "permission": {
            "className": "",
            "properties": {}
        },
        "noPermissionMessage": "",
        "postProcessor": {
            "className": "",
            "properties": {}
        },
        "postProcessorRunOn": "create"
    },
    "elements": [
        {
            "className": "org.joget.apps.form.model.Section",
            "properties": {
                "label": "",
                "id": "section1"
            },
            "elements": [
                {
                    "className": "org.joget.apps.form.model.Column",
                    "properties": {
                        "width": "100%"
                    },
                    "elements": [
                        {
                            "className": "org.joget.apps.form.lib.TextField",
                            "properties": {
                                "id": "code",
                                "label": "Code",
                                "validator": {
                                    "className": "org.joget.apps.form.lib.DuplicateValueValidator",
                                    "properties": {
                                        "formDefId": "md16livestockType",
                                        "fieldId": "code",
                                        "errorDuplicateMsg": "This livestock type code already exists",
                                        "mandatory": "true",
                                        "regex": "",
                                        "errorFormatMsg": ""
                                    }
                                },
                                "encryption": "",
                                "readonly": "",
                                "style": "",
                                "readonlyLabel": "",
                                "storeNumeric": "",
                                "value": "",
                                "maxlength": "30",
                                "requiredSanitize": "",
                                "placeholder": "",
                                "size": "",
                                "workflowVariable": ""
                            }
                        },
                        {
                            "className": "org.joget.apps.form.lib.SelectBox",
                            "properties": {
                                "id": "category",
                                "label": "Livestock Category",
                                "readonly": "",
                                "multiple": "",
                                "readonlyLabel": "",
                                "options": [],
                                "optionsBinder": {
                                    "className": "org.joget.apps.form.lib.FormOptionsBinder",
                                    "properties": {
                                        "formDefId": "md161livestockCategory",
                                        "idColumn": "code",
                                        "labelColumn": "name",
                                        "groupingColumn": "",
                                        "extraCondition": "",
                                        "addEmptyOption": "true",
                                        "emptyLabel": "",
                                        "useAjax": "",
                                        "cacheInterval": ""
                                    }
                                },
                                "value": "",
                                "validator": {
                                    "className": "org.joget.apps.form.lib.DefaultValidator",
                                    "properties": {
                                        "mandatory": "true",
                                        "type": "",
                                        "message": ""
                                    }
                                },
                                "controlField": "",
                                "size": "",
                                "workflowVariable": ""
                            }
                        },
                        {
                            "className": "org.joget.apps.form.lib.TextField",
                            "properties": {
                                "id": "name",
                                "label": "Name",
                                "validator": {
                                    "className": "org.joget.apps.form.lib.DefaultValidator",
                                    "properties": {
                                        "mandatory": "true",
                                        "type": "",
                                        "message": ""
                                    }
                                },
                                "encryption": "",
                                "readonly": "",
                                "style": "",
                                "readonlyLabel": "",
                                "storeNumeric": "",
                                "value": "",
                                "maxlength": "100",
                                "requiredSanitize": "",
                                "placeholder": "",
                                "size": "",
                                "workflowVariable": ""
                            }
                        },
                        {
                            "className": "org.joget.apps.form.lib.Radio",
                            "properties": {
                                "id": "isActive",
                                "label": "Active",
                                "options": [
                                    {
                                        "value": "Y",
                                        "label": "Yes",
                                        "grouping": ""
                                    },
                                    {
                                        "value": "N",
                                        "label": "No",
                                        "grouping": ""
                                    }
                                ],
                                "optionsBinder": {
                                    "className": "",
                                    "properties": {}
                                },
                                "value": "Y",
                                "validator": {
                                    "className": "org.joget.apps.form.lib.DefaultValidator",
                                    "properties": {
                                        "mandatory": "true",
                                        "type": "",
                                        "message": ""
                                    }
                                },
                                "readonly": "",
                                "readonlyLabel": "",
                                "controlField": "",
                                "workflowVariable": ""
                            }
                        }
                    ]
                }
            ]
        }
    ]
}
